Metadata-Version: 2.1
Name: dtais-test
Version: 0.0.1
Summary: dtais cmd test
Home-page: https://github.com/
Author: Lazarrt
Author-email: LazarrtLi@outlook.com
Classifier: Programming Language :: Python :: 3
Classifier: License :: OSI Approved :: MIT License
Classifier: Operating System :: OS Independent
